datapizza/tools/web_fetch/__init__.py
datapizza/tools/web_fetch/base.py
datapizza_ai_tools_web_fetch-0.0.2.dist-info/METADATA
datapizza_ai_tools_web_fetch-0.0.2.dist-info/WHEEL
datapizza_ai_tools_web_fetch-0.0.2.dist-info/RECORD
